
[
    {
      "id": 1,
      "img":"doctorsImg/1.jpeg",
      "name": "Dr. John Smith",
      "qualification": ["MBBS", "MD Internal Medicine","PharmD","DPT"],
      "specialization": ["Cardiologist", "Internal Medicine", "Interventional Cardiology"]
    },
    {
      "id": 2,
      "img":"doctorsImg/2.jpeg",
      "name": "Dr. Emily Johnson",
      "qualification": ["MBBS", "MD Dermatology","PsyD","DVM"],
      "specialization": ["Dermatologist", "Cosmetic Dermatology", "Pediatric Dermatology"]
    },
    {
      "id": 3,
      "img":"doctorsImg/3.jpeg",
      "name": "Dr. Michael Davis",
      "qualification": ["MBBS", "MS Orthopedics","EdD","DHSc"],
      "specialization": ["Orthopedic Surgeon", "Sports Medicine", "Joint Replacement"]
    },
    {
      "id": 4,
      "img":"doctorsImg/4.jpeg",
      "name": "Dr. Sarah Wilson",
      "qualification": ["MBBS", "MD Psychiatry","DPM","DMD"],
      "specialization": ["Psychiatrist", "Child and Adolescent Psychiatry", "Geriatric Psychiatry"]
    },
    {
    },
    {
      "id": 5,
      "img":"doctorsImg/5.jpeg",
      "name": "Dr. Laura Brown",
      "qualification": ["MBBS", "MS Obstetrics and Gynecology"],
      "specialization":  ["Gynecologist", "Maternal-Fetal Medicine", "Reproductive Endocrinology"]
    },
    {
      "id": 6,
      "img":"doctorsImg/6.jpeg",
      "name": "Dr. Daniel White",
      "qualification": ["MBBS", "MD Pediatrics"],
      "specialization": ["Pediatrician", "Neonatology", "Pediatric Cardiology"]
    },
    {
      "id": 7,
      "img":"doctorsImg/7.jpeg",
      "name": "Dr. Olivia Miller",
      "qualification": ["MBBS", "MD Neurology"],
      "specialization": ["Neurologist", "Movement Disorders", "Neurocritical Care"]
    },
    {
      "id": 8,
      "img":"doctorsImg/8.jpeg",
      "name": "Dr. William Taylor",
      "qualification": ["MBBS", "MD Ophthalmology"],
      "specialization": ["Nephrologist", "Transplant Nephrology", "Hypertension"]
    },
    {
      "id": 9,
      "img":"doctorsImg/9.jpeg",
      "name": "Dr. Samantha Clark",
      "qualification": ["MBBS", "MD Dentistry"],
      "specialization": ["Ophthalmologist", "Retina Specialist", "Cornea and External Diseases"]
    },
    {
      "id": 10,
      "img":"doctorsImg/10.jpeg",
      "name": "Dr. Benjamin Turner",
      "qualification": ["MBBS", "MD Gastroenterology"],
      "specialization": ["Gastroenterologist", "Hepatology", "Pancreatic Diseases"]
    },
    {
      "id": 11,
      "img":"doctorsImg/11.jpeg",
      "name": "Dr. Sophia Lewis",
      "qualification": ["MBBS", "MD Urology"],
      "specialization": ["Urologist", "Female Urology", "Reconstructive Urology"]
    },
    {
      "id": 12,
      "img":"doctorsImg/12.jpeg",
      "name": "Dr. Ethan Moore",
      "qualification": ["MBBS", "MD Radiology"],
      "specialization": ["Radiologist", "Interventional Radiology", "Musculoskeletal Radiology"]
    },
    {
      "id": 13,
      "img":"doctorsImg/13.jpeg",
      "name": "Dr. Ava Garcia",
      "qualification": ["MBBS", "MD Nephrology"],
      "specialization": ["Nephrologist", "Transplant Nephrology", "Hypertension"]
    },
    {
      "id": 14,
      "img":"doctorsImg/14.jpeg",
      "name": "Dr. Noah Hall",
      "qualification": ["MBBS", "MD Pulmonology"],
      "specialization": ["Pulmonologist", "Critical Care Medicine", "Sleep Medicine"]
    },
    {
      "id": 15,
      "img":"doctorsImg/15.jpeg",
      "name": "Dr. Madison King",
      "qualification": ["MBBS", "MD Endocrinology"],
      "specialization": ["Endocrinologist", "Thyroid Disorders", "Diabetes Management"]
    }
  ]
  